example/example/__init__.py
example/example/main.py
example/out/__init__.py
example/out/main.py
example/out/test_main.py
example/tests/__init__.py
example/tests/test_main.py
py_backwards/__init__.py
py_backwards/compiler.py
py_backwards/conf.py
py_backwards/const.py
py_backwards/exceptions.py
py_backwards/files.py
py_backwards/main.py
py_backwards/messages.py
py_backwards/types.py
py_backwards/transformers/__init__.py
py_backwards/transformers/base.py
py_backwards/transformers/class_without_bases.py
py_backwards/transformers/dict_unpacking.py
py_backwards/transformers/formatted_values.py
py_backwards/transformers/functions_annotations.py
py_backwards/transformers/import_pathlib.py
py_backwards/transformers/metaclass.py
py_backwards/transformers/python2_future.py
py_backwards/transformers/return_from_generator.py
py_backwards/transformers/six_moves.py
py_backwards/transformers/starred_unpacking.py
py_backwards/transformers/string_types.py
py_backwards/transformers/super_without_arguments.py
py_backwards/transformers/variables_annotations.py
py_backwards/transformers/yield_from.py
py_backwards/utils/__init__.py
py_backwards/utils/helpers.py
py_backwards/utils/snippet.py
py_backwards/utils/tree.py
py_backwards-0.7.dist-info/DESCRIPTION.rst
py_backwards-0.7.dist-info/METADATA
py_backwards-0.7.dist-info/RECORD
py_backwards-0.7.dist-info/WHEEL
py_backwards-0.7.dist-info/entry_points.txt
py_backwards-0.7.dist-info/metadata.json
py_backwards-0.7.dist-info/top_level.txt
