Metadata-Version: 1.0
Name: py-backwards
Version: 0.7
Summary: Translates python code for older versions
Home-page: https://github.com/nvbn/py-backwards
Author: Vladimir Iakovlev
Author-email: nvbn.rm@gmail.com
License: MIT
Platform: UNKNOWN
